ocx_versioning/__init__.py
ocx_versioning/__main__.py
ocx_versioning/xsdata_package.py
ocx_versioning-1.0.0.dist-info/LICENSE
ocx_versioning-1.0.0.dist-info/METADATA
ocx_versioning-1.0.0.dist-info/WHEEL
ocx_versioning-1.0.0.dist-info/RECORD
