Metadata-Version: 2.1
Name: ocx_versioning
Version: 1.0.0
Summary: Utility python scripts for managing OCX schema versioning according to PEP 440
Author: ocastrup
Author-email: ole.christian.astrup@dnv.com
Requires-Python: >=3.11,<4.0
Classifier: Programming Language :: Python :: 3
Classifier: Programming Language :: Python :: 3.11
Requires-Dist: click
Requires-Dist: lxml
Requires-Dist: packaging (>=23.1,<24.0)
Requires-Dist: soap
Requires-Dist: tbump
Requires-Dist: xsdata
